ontocubes/__init__.py
ontocubes-0.1.1.dist-info/METADATA
ontocubes-0.1.1.dist-info/WHEEL
ontocubes-0.1.1.dist-info/RECORD
