Metadata-Version: 2.4
Name: ontocubes
Version: 0.1.1
Summary: Universal ontological cube framework - represent any entity as a 5-layer cube. COMING SOON.
Project-URL: Homepage, https://github.com/lifeaitools/ontocubes
Author-email: LifeAiTools <dev@lifeaitools.com>
License-Expression: MIT
Keywords: cubes,entity-modeling,knowledge-representation,ontology
Classifier: Development Status :: 1 - Planning
Classifier: Intended Audience :: Developers
Classifier: License :: OSI Approved :: MIT License
Classifier: Programming Language :: Python :: 3
Classifier: Programming Language :: Python :: 3.10
Classifier: Programming Language :: Python :: 3.11
Classifier: Programming Language :: Python :: 3.12
Requires-Python: >=3.10
